{
    "SRC_CONNECTION": "KAFKA_PYTHON",
    "TGT_CONNECTION": "Postgres_Connection_First",
    "TGT_TABLE_NAME": "XLA_TRANSACTION_HEADERS",
    "TGT_SCHEMA_NAME": "BMS_BM_ERP_FUSION_ODS",
    "TABLE_UNIQUE_COLUMNS": "APPLICATION_ID, EVENT_ID",
    "DEL_TGT_SCHEMA_NAME": "BMS_BM_ERP_FUSION_ODS_STAGE",
    "PRE_TRIGGER_TASK": {
        "PRT_OTHER_TGT_SQL": [],
        "PRT_TRUNCATE_TGT_TABLE_FULL_SQL": [
            "TRUNCATE TABLE BMS_BM_ERP_FUSION_ODS.XLA_TRANSACTION_HEADERS ;"
        ],
        "PRT_DROP_TGT_INDEXES_FULL_SQL": [
            "DROP INDEX  IF EXISTS  BMS_BM_ERP_FUSION_ODS.XLA_TRANSACTION_HEADERS_U1;"
        ],
        "PRT_TRUNCATE_TGT_TABLE_INC_SQL": [],
        "PRT_DROP_TGT_INDEXES_INC_SQL": []
    },
    "DATA_FLOW_TASK": {
        "DFT_READ_CSV_BATCHES": 5000,
        "DFT_WRITE_TGT_BATCHES": 5000,
        "DFT_PERFORM_TGT_TRANSFORM": "Y",
        "DFT_TGT_TABLE_COLUMNS": "APPLICATION_ID,CHAR1,CHAR10,CHAR11,CHAR12,CHAR13,CHAR14,CHAR15,CHAR16,CHAR17,CHAR18,CHAR19,CHAR2,CHAR20,CHAR21,CHAR22,CHAR23,CHAR24,CHAR25,CHAR26,CHAR27,CHAR28,CHAR29,CHAR3,CHAR30,CHAR31,CHAR32,CHAR33,CHAR34,CHAR35,CHAR36,CHAR37,CHAR38,CHAR39,CHAR4,CHAR40,CHAR41,CHAR42,CHAR43,CHAR44,CHAR45,CHAR46,CHAR47,CHAR48,CHAR49,CHAR5,CHAR50,CHAR6,CHAR7,CHAR8,CHAR9,CREATED_BY,CREATION_DATE,DATE1,DATE10,DATE2,DATE3,DATE4,DATE5,DATE6,DATE7,DATE8,DATE9,EVENT_ID,JOB_DEFINITION_NAME,JOB_DEFINITION_PACKAGE,LAST_UPDATE_DATE,LAST_UPDATE_LOGIN,LAST_UPDATED_BY,LONG_CHAR1,LONG_CHAR2,LONG_CHAR3,LONG_CHAR4,LONG_CHAR5,NUMBER1,NUMBER10,NUMBER2,NUMBER3,NUMBER4,NUMBER5,NUMBER6,NUMBER7,NUMBER8,NUMBER9,OBJECT_VERSION_NUMBER,REQUEST_ID,TRANSACTION_DATE,TRANSACTION_NUMBER,TRANSACTION_REVERSAL_FLAG",
        "DFT_SRC_CSV_COLUMNS_DTYPES": {
            "TRANSACTIONHEADERAPPLICATIONID": "float",
            "TRANSACTIONHEADERCHAR1": "str",
            "TRANSACTIONHEADERCHAR10": "str",
            "TRANSACTIONHEADERCHAR11": "str",
            "TRANSACTIONHEADERCHAR12": "str",
            "TRANSACTIONHEADERCHAR13": "str",
            "TRANSACTIONHEADERCHAR14": "str",
            "TRANSACTIONHEADERCHAR15": "str",
            "TRANSACTIONHEADERCHAR16": "str",
            "TRANSACTIONHEADERCHAR17": "str",
            "TRANSACTIONHEADERCHAR18": "str",
            "TRANSACTIONHEADERCHAR19": "str",
            "TRANSACTIONHEADERCHAR2": "str",
            "TRANSACTIONHEADERCHAR20": "str",
            "TRANSACTIONHEADERCHAR21": "str",
            "TRANSACTIONHEADERCHAR22": "str",
            "TRANSACTIONHEADERCHAR23": "str",
            "TRANSACTIONHEADERCHAR24": "str",
            "TRANSACTIONHEADERCHAR25": "str",
            "TRANSACTIONHEADERCHAR26": "str",
            "TRANSACTIONHEADERCHAR27": "str",
            "TRANSACTIONHEADERCHAR28": "str",
            "TRANSACTIONHEADERCHAR29": "str",
            "TRANSACTIONHEADERCHAR3": "str",
            "TRANSACTIONHEADERCHAR30": "str",
            "TRANSACTIONHEADERCHAR31": "str",
            "TRANSACTIONHEADERCHAR32": "str",
            "TRANSACTIONHEADERCHAR33": "str",
            "TRANSACTIONHEADERCHAR34": "str",
            "TRANSACTIONHEADERCHAR35": "str",
            "TRANSACTIONHEADERCHAR36": "str",
            "TRANSACTIONHEADERCHAR37": "str",
            "TRANSACTIONHEADERCHAR38": "str",
            "TRANSACTIONHEADERCHAR39": "str",
            "TRANSACTIONHEADERCHAR4": "str",
            "TRANSACTIONHEADERCHAR40": "str",
            "TRANSACTIONHEADERCHAR41": "str",
            "TRANSACTIONHEADERCHAR42": "str",
            "TRANSACTIONHEADERCHAR43": "str",
            "TRANSACTIONHEADERCHAR44": "str",
            "TRANSACTIONHEADERCHAR45": "str",
            "TRANSACTIONHEADERCHAR46": "str",
            "TRANSACTIONHEADERCHAR47": "str",
            "TRANSACTIONHEADERCHAR48": "str",
            "TRANSACTIONHEADERCHAR49": "str",
            "TRANSACTIONHEADERCHAR5": "str",
            "TRANSACTIONHEADERCHAR50": "str",
            "TRANSACTIONHEADERCHAR6": "str",
            "TRANSACTIONHEADERCHAR7": "str",
            "TRANSACTIONHEADERCHAR8": "str",
            "TRANSACTIONHEADERCHAR9": "str",
            "TRANSACTIONHEADERCREATEDBY": "str",
            "TRANSACTIONHEADERCREATIONDATE": "str",
            "TRANSACTIONHEADERDATE1": "str",
            "TRANSACTIONHEADERDATE10": "str",
            "TRANSACTIONHEADERDATE2": "str",
            "TRANSACTIONHEADERDATE3": "str",
            "TRANSACTIONHEADERDATE4": "str",
            "TRANSACTIONHEADERDATE5": "str",
            "TRANSACTIONHEADERDATE6": "str",
            "TRANSACTIONHEADERDATE7": "str",
            "TRANSACTIONHEADERDATE8": "str",
            "TRANSACTIONHEADERDATE9": "str",
            "TRANSACTIONHEADEREVENTID": "float",
            "TRANSACTIONHEADERJOBDEFINITIONNAME": "str",
            "TRANSACTIONHEADERJOBDEFINITIONPACKAGE": "str",
            "TRANSACTIONHEADERLASTUPDATEDATE": "str",
            "TRANSACTIONHEADERLASTUPDATELOGIN": "str",
            "TRANSACTIONHEADERLASTUPDATEDBY": "str",
            "TRANSACTIONHEADERLONGCHAR1": "str",
            "TRANSACTIONHEADERLONGCHAR2": "str",
            "TRANSACTIONHEADERLONGCHAR3": "str",
            "TRANSACTIONHEADERLONGCHAR4": "str",
            "TRANSACTIONHEADERLONGCHAR5": "str",
            "TRANSACTIONHEADERNUMBER1": "float",
            "TRANSACTIONHEADERNUMBER10": "float",
            "TRANSACTIONHEADERNUMBER2": "float",
            "TRANSACTIONHEADERNUMBER3": "float",
            "TRANSACTIONHEADERNUMBER4": "float",
            "TRANSACTIONHEADERNUMBER5": "float",
            "TRANSACTIONHEADERNUMBER6": "float",
            "TRANSACTIONHEADERNUMBER7": "float",
            "TRANSACTIONHEADERNUMBER8": "float",
            "TRANSACTIONHEADERNUMBER9": "float",
            "TRANSACTIONHEADEROBJECTVERSIONNUMBER": "float",
            "TRANSACTIONHEADERREQUESTID": "float",
            "TRANSACTIONHEADERTRANSACTIONDATE": "str",
            "TRANSACTIONHEADERTRANSACTIONNUMBER": "str",
            "TRANSACTIONHEADERTRANSACTIONREVERSALFLAG": "str"
        },
        "DFT_SRC_CSV_COLUMNS": "TRANSACTIONHEADERAPPLICATIONID,TRANSACTIONHEADERCHAR1,TRANSACTIONHEADERCHAR10,TRANSACTIONHEADERCHAR11,TRANSACTIONHEADERCHAR12,TRANSACTIONHEADERCHAR13,TRANSACTIONHEADERCHAR14,TRANSACTIONHEADERCHAR15,TRANSACTIONHEADERCHAR16,TRANSACTIONHEADERCHAR17,TRANSACTIONHEADERCHAR18,TRANSACTIONHEADERCHAR19,TRANSACTIONHEADERCHAR2,TRANSACTIONHEADERCHAR20,TRANSACTIONHEADERCHAR21,TRANSACTIONHEADERCHAR22,TRANSACTIONHEADERCHAR23,TRANSACTIONHEADERCHAR24,TRANSACTIONHEADERCHAR25,TRANSACTIONHEADERCHAR26,TRANSACTIONHEADERCHAR27,TRANSACTIONHEADERCHAR28,TRANSACTIONHEADERCHAR29,TRANSACTIONHEADERCHAR3,TRANSACTIONHEADERCHAR30,TRANSACTIONHEADERCHAR31,TRANSACTIONHEADERCHAR32,TRANSACTIONHEADERCHAR33,TRANSACTIONHEADERCHAR34,TRANSACTIONHEADERCHAR35,TRANSACTIONHEADERCHAR36,TRANSACTIONHEADERCHAR37,TRANSACTIONHEADERCHAR38,TRANSACTIONHEADERCHAR39,TRANSACTIONHEADERCHAR4,TRANSACTIONHEADERCHAR40,TRANSACTIONHEADERCHAR41,TRANSACTIONHEADERCHAR42,TRANSACTIONHEADERCHAR43,TRANSACTIONHEADERCHAR44,TRANSACTIONHEADERCHAR45,TRANSACTIONHEADERCHAR46,TRANSACTIONHEADERCHAR47,TRANSACTIONHEADERCHAR48,TRANSACTIONHEADERCHAR49,TRANSACTIONHEADERCHAR5,TRANSACTIONHEADERCHAR50,TRANSACTIONHEADERCHAR6,TRANSACTIONHEADERCHAR7,TRANSACTIONHEADERCHAR8,TRANSACTIONHEADERCHAR9,TRANSACTIONHEADERCREATEDBY,TRANSACTIONHEADERCREATIONDATE,TRANSACTIONHEADERDATE1,TRANSACTIONHEADERDATE10,TRANSACTIONHEADERDATE2,TRANSACTIONHEADERDATE3,TRANSACTIONHEADERDATE4,TRANSACTIONHEADERDATE5,TRANSACTIONHEADERDATE6,TRANSACTIONHEADERDATE7,TRANSACTIONHEADERDATE8,TRANSACTIONHEADERDATE9,TRANSACTIONHEADEREVENTID,TRANSACTIONHEADERJOBDEFINITIONNAME,TRANSACTIONHEADERJOBDEFINITIONPACKAGE,TRANSACTIONHEADERLASTUPDATEDATE,TRANSACTIONHEADERLASTUPDATELOGIN,TRANSACTIONHEADERLASTUPDATEDBY,TRANSACTIONHEADERLONGCHAR1,TRANSACTIONHEADERLONGCHAR2,TRANSACTIONHEADERLONGCHAR3,TRANSACTIONHEADERLONGCHAR4,TRANSACTIONHEADERLONGCHAR5,TRANSACTIONHEADERNUMBER1,TRANSACTIONHEADERNUMBER10,TRANSACTIONHEADERNUMBER2,TRANSACTIONHEADERNUMBER3,TRANSACTIONHEADERNUMBER4,TRANSACTIONHEADERNUMBER5,TRANSACTIONHEADERNUMBER6,TRANSACTIONHEADERNUMBER7,TRANSACTIONHEADERNUMBER8,TRANSACTIONHEADERNUMBER9,TRANSACTIONHEADEROBJECTVERSIONNUMBER,TRANSACTIONHEADERREQUESTID,TRANSACTIONHEADERTRANSACTIONDATE,TRANSACTIONHEADERTRANSACTIONNUMBER,TRANSACTIONHEADERTRANSACTIONREVERSALFLAG",
        "DFT_INSERT_TGT_FULL_SQL": [
            "INSERT INTO BMS_BM_ERP_FUSION_ODS.XLA_TRANSACTION_HEADERS  (APPLICATION_ID,CHAR1,CHAR10,CHAR11,CHAR12,CHAR13,CHAR14,CHAR15,CHAR16,CHAR17,CHAR18,CHAR19,CHAR2,CHAR20,CHAR21,CHAR22,CHAR23,CHAR24,CHAR25,CHAR26,CHAR27,CHAR28,CHAR29,CHAR3,CHAR30,CHAR31,CHAR32,CHAR33,CHAR34,CHAR35,CHAR36,CHAR37,CHAR38,CHAR39,CHAR4,CHAR40,CHAR41,CHAR42,CHAR43,CHAR44,CHAR45,CHAR46,CHAR47,CHAR48,CHAR49,CHAR5,CHAR50,CHAR6,CHAR7,CHAR8,CHAR9,CREATED_BY,CREATION_DATE,DATE1,DATE10,DATE2,DATE3,DATE4,DATE5,DATE6,DATE7,DATE8,DATE9,EVENT_ID,JOB_DEFINITION_NAME,JOB_DEFINITION_PACKAGE,LAST_UPDATE_DATE,LAST_UPDATE_LOGIN,LAST_UPDATED_BY,LONG_CHAR1,LONG_CHAR2,LONG_CHAR3,LONG_CHAR4,LONG_CHAR5,NUMBER1,NUMBER10,NUMBER2,NUMBER3,NUMBER4,NUMBER5,NUMBER6,NUMBER7,NUMBER8,NUMBER9,OBJECT_VERSION_NUMBER,REQUEST_ID,TRANSACTION_DATE,TRANSACTION_NUMBER,TRANSACTION_REVERSAL_FLAG) VALUES %s "
        ],
        "DFT_INSERT_TGT_INC_SQL": [
            "INSERT INTO BMS_BM_ERP_FUSION_ODS.XLA_TRANSACTION_HEADERS  (APPLICATION_ID,CHAR1,CHAR10,CHAR11,CHAR12,CHAR13,CHAR14,CHAR15,CHAR16,CHAR17,CHAR18,CHAR19,CHAR2,CHAR20,CHAR21,CHAR22,CHAR23,CHAR24,CHAR25,CHAR26,CHAR27,CHAR28,CHAR29,CHAR3,CHAR30,CHAR31,CHAR32,CHAR33,CHAR34,CHAR35,CHAR36,CHAR37,CHAR38,CHAR39,CHAR4,CHAR40,CHAR41,CHAR42,CHAR43,CHAR44,CHAR45,CHAR46,CHAR47,CHAR48,CHAR49,CHAR5,CHAR50,CHAR6,CHAR7,CHAR8,CHAR9,CREATED_BY,CREATION_DATE,DATE1,DATE10,DATE2,DATE3,DATE4,DATE5,DATE6,DATE7,DATE8,DATE9,EVENT_ID,JOB_DEFINITION_NAME,JOB_DEFINITION_PACKAGE,LAST_UPDATE_DATE,LAST_UPDATE_LOGIN,LAST_UPDATED_BY,LONG_CHAR1,LONG_CHAR2,LONG_CHAR3,LONG_CHAR4,LONG_CHAR5,NUMBER1,NUMBER10,NUMBER2,NUMBER3,NUMBER4,NUMBER5,NUMBER6,NUMBER7,NUMBER8,NUMBER9,OBJECT_VERSION_NUMBER,REQUEST_ID,TRANSACTION_DATE,TRANSACTION_NUMBER,TRANSACTION_REVERSAL_FLAG) VALUES %s   ON CONFLICT (APPLICATION_ID, EVENT_ID) DO UPDATE SET CHAR1=EXCLUDED.CHAR1,CHAR10=EXCLUDED.CHAR10,CHAR11=EXCLUDED.CHAR11,CHAR12=EXCLUDED.CHAR12,CHAR13=EXCLUDED.CHAR13,CHAR14=EXCLUDED.CHAR14,CHAR15=EXCLUDED.CHAR15,CHAR16=EXCLUDED.CHAR16,CHAR17=EXCLUDED.CHAR17,CHAR18=EXCLUDED.CHAR18,CHAR19=EXCLUDED.CHAR19,CHAR2=EXCLUDED.CHAR2,CHAR20=EXCLUDED.CHAR20,CHAR21=EXCLUDED.CHAR21,CHAR22=EXCLUDED.CHAR22,CHAR23=EXCLUDED.CHAR23,CHAR24=EXCLUDED.CHAR24,CHAR25=EXCLUDED.CHAR25,CHAR26=EXCLUDED.CHAR26,CHAR27=EXCLUDED.CHAR27,CHAR28=EXCLUDED.CHAR28,CHAR29=EXCLUDED.CHAR29,CHAR3=EXCLUDED.CHAR3,CHAR30=EXCLUDED.CHAR30,CHAR31=EXCLUDED.CHAR31,CHAR32=EXCLUDED.CHAR32,CHAR33=EXCLUDED.CHAR33,CHAR34=EXCLUDED.CHAR34,CHAR35=EXCLUDED.CHAR35,CHAR36=EXCLUDED.CHAR36,CHAR37=EXCLUDED.CHAR37,CHAR38=EXCLUDED.CHAR38,CHAR39=EXCLUDED.CHAR39,CHAR4=EXCLUDED.CHAR4,CHAR40=EXCLUDED.CHAR40,CHAR41=EXCLUDED.CHAR41,CHAR42=EXCLUDED.CHAR42,CHAR43=EXCLUDED.CHAR43,CHAR44=EXCLUDED.CHAR44,CHAR45=EXCLUDED.CHAR45,CHAR46=EXCLUDED.CHAR46,CHAR47=EXCLUDED.CHAR47,CHAR48=EXCLUDED.CHAR48,CHAR49=EXCLUDED.CHAR49,CHAR5=EXCLUDED.CHAR5,CHAR50=EXCLUDED.CHAR50,CHAR6=EXCLUDED.CHAR6,CHAR7=EXCLUDED.CHAR7,CHAR8=EXCLUDED.CHAR8,CHAR9=EXCLUDED.CHAR9,CREATED_BY=EXCLUDED.CREATED_BY,CREATION_DATE=EXCLUDED.CREATION_DATE,DATE1=EXCLUDED.DATE1,DATE10=EXCLUDED.DATE10,DATE2=EXCLUDED.DATE2,DATE3=EXCLUDED.DATE3,DATE4=EXCLUDED.DATE4,DATE5=EXCLUDED.DATE5,DATE6=EXCLUDED.DATE6,DATE7=EXCLUDED.DATE7,DATE8=EXCLUDED.DATE8,DATE9=EXCLUDED.DATE9,JOB_DEFINITION_NAME=EXCLUDED.JOB_DEFINITION_NAME,JOB_DEFINITION_PACKAGE=EXCLUDED.JOB_DEFINITION_PACKAGE,LAST_UPDATE_DATE=EXCLUDED.LAST_UPDATE_DATE,LAST_UPDATE_LOGIN=EXCLUDED.LAST_UPDATE_LOGIN,LAST_UPDATED_BY=EXCLUDED.LAST_UPDATED_BY,LONG_CHAR1=EXCLUDED.LONG_CHAR1,LONG_CHAR2=EXCLUDED.LONG_CHAR2,LONG_CHAR3=EXCLUDED.LONG_CHAR3,LONG_CHAR4=EXCLUDED.LONG_CHAR4,LONG_CHAR5=EXCLUDED.LONG_CHAR5,NUMBER1=EXCLUDED.NUMBER1,NUMBER10=EXCLUDED.NUMBER10,NUMBER2=EXCLUDED.NUMBER2,NUMBER3=EXCLUDED.NUMBER3,NUMBER4=EXCLUDED.NUMBER4,NUMBER5=EXCLUDED.NUMBER5,NUMBER6=EXCLUDED.NUMBER6,NUMBER7=EXCLUDED.NUMBER7,NUMBER8=EXCLUDED.NUMBER8,NUMBER9=EXCLUDED.NUMBER9,OBJECT_VERSION_NUMBER=EXCLUDED.OBJECT_VERSION_NUMBER,REQUEST_ID=EXCLUDED.REQUEST_ID,TRANSACTION_DATE=EXCLUDED.TRANSACTION_DATE,TRANSACTION_NUMBER=EXCLUDED.TRANSACTION_NUMBER,TRANSACTION_REVERSAL_FLAG=EXCLUDED.TRANSACTION_REVERSAL_FLAG,DWH_UPDATE_DT = now();"
        ]
    },
    "DELETE_TASK": {
        "DEL_ENABLE_FLAG": "N",
        "DEL_HARD_DELETE_SQL": [
            "DELETE FROM BMS_BM_ERP_FUSION_ODS.XLA_TRANSACTION_HEADERS WHERE (APPLICATION_ID, EVENT_ID) IN (SELECT APPLICATION_ID, EVENT_ID FROM BMS_BM_ERP_FUSION_ODS_STAGE.XLA_TRANSACTION_HEADERS_DEL);"
        ]
    },
    "POST_TRIGGER_TASK": {
        "PST_OTHER_TGT_SQL": [],
        "PST_CREATE_INDEX_TGT_FULL_SQL": [
            "CREATE UNIQUE INDEX XLA_TRANSACTION_HEADERS_U1 ON BMS_BM_ERP_FUSION_ODS.XLA_TRANSACTION_HEADERS (APPLICATION_ID, EVENT_ID) ;"
        ],
        "PST_CREATE_INDEX_TGT_INC_SQL": []
    }
}